micro_logging_ext/__init__.py
micro_logging_ext-1.0.1.dist-info/METADATA
micro_logging_ext-1.0.1.dist-info/WHEEL
micro_logging_ext-1.0.1.dist-info/top_level.txt
micro_logging_ext-1.0.1.dist-info/RECORD
