Metadata-Version: 2.1
Name: micro-logging-ext
Version: 1.0.1
Summary: micro_logging_ext
Home-page: https://github.com/alhazmy13/logging_ext
Author: Alhazmy13
Author-email: me@alhazmy13.net
License: MIT
Platform: UNKNOWN
